nonebot_plugin_image_summary/__init__.py
nonebot_plugin_image_summary/config.py
nonebot_plugin_image_summary/data_manager.py
nonebot_plugin_image_summary-0.1.5.dist-info/METADATA
nonebot_plugin_image_summary-0.1.5.dist-info/WHEEL
nonebot_plugin_image_summary-0.1.5.dist-info/RECORD
