Metadata-Version: 2.4
Name: nonebot-plugin-image-summary
Version: 0.1.5
Summary: NoneBot2 插件：拦截所有图片消息并注入摘要/外显文本。
Project-URL: Homepage, https://github.com/YourGitHubUsername/nonebot-plugin-image-summary
Project-URL: Issues, https://github.com/YourGitHubUsername/nonebot-plugin-image-summary/issues
Author-email: Your Name <your_email@example.com>
Keywords: image,nonebot2,plugin,summary
Requires-Python: >=3.8
Requires-Dist: aiohttp
Requires-Dist: nonebot-adapter-onebot>=2.0.0
Requires-Dist: nonebot2>=2.0.0
Requires-Dist: pydantic>=1.8
